notoken887/__init__.py
notoken887/encryptor.py
notoken887/main.py
notoken887-1.26.40.dist-info/METADATA
notoken887-1.26.40.dist-info/WHEEL
notoken887-1.26.40.dist-info/entry_points.txt
notoken887-1.26.40.dist-info/top_level.txt
notoken887-1.26.40.dist-info/RECORD
