Metadata-Version: 2.1
Name: notoken887
Version: 1.26.40
Summary: my obfuscation test lib
Home-page: https://thugging.org
Author: Yous
Author-email: hitler@gmail.com
Classifier: Programming Language :: Python :: 3
Classifier: License :: OSI Approved :: MIT License
Classifier: Operating System :: OS Independent
Requires-Python: >=3.6
